openvancy/__init__.py
openvancy/core.py
openvancy/openvancy.py
openvancy/openvancy_views.py
openvancy/pipeline/__init__.py
openvancy/pipeline/defect_analisys.py
openvancy/runner/__init__.py
openvancy/runner/ws_method.py
openvancy/training/__init__.py
openvancy/training/preparer.py
openvancy/training/training_finger.py
openvancy/training/training_graph.py
openvancy/utils/__init__.py
openvancy/utils/config_loader.py
openvancy/utils/cristal_structure_gen.py
openvancy/utils/deformation_analyzer.py
openvancy/utils/key_files_separator.py
openvancy/views/__init__.py
openvancy/views/main_vista.py
openvancy-0.0.4.0.dist-info/METADATA
openvancy-0.0.4.0.dist-info/WHEEL
openvancy-0.0.4.0.dist-info/entry_points.txt
openvancy-0.0.4.0.dist-info/top_level.txt
openvancy-0.0.4.0.dist-info/RECORD
